logger_tt/__init__.py
logger_tt/__init__.pyi
logger_tt/capture.py
logger_tt/core.py
logger_tt/handlers.py
logger_tt/inspector.py
logger_tt/log_config.json
logger_tt/log_config.yaml
logger_tt-1.7.3.dist-info/LICENSE
logger_tt-1.7.3.dist-info/METADATA
logger_tt-1.7.3.dist-info/WHEEL
logger_tt-1.7.3.dist-info/top_level.txt
logger_tt-1.7.3.dist-info/RECORD
