Metadata-Version: 2.1
Name: logger_tt
Version: 1.7.3
Summary: Make logging simple, log even exception that you forgot to catch. Make multiprocessing logging becomes a breeze
Home-page: https://github.com/Dragon2fly/logger_tt
Author: Nguyen Ba Duc Tin
Author-email: nguyenbaduc.tin@gmail.com
License: MIT
Platform: Any platform -- don't need Windows
Classifier: Development Status :: 5 - Production/Stable
Classifier: Intended Audience :: Developers
Classifier: License :: OSI Approved :: MIT License
Classifier: Programming Language :: Python
Classifier: Programming Language :: Python :: 3.6
Classifier: Programming Language :: Python :: 3.7
Classifier: Programming Language :: Python :: 3.8
Classifier: Programming Language :: Python :: 3.9
Classifier: Programming Language :: Python :: 3.10
Classifier: Programming Language :: Python :: 3.11
Classifier: Operating System :: OS Independent
Classifier: Topic :: System :: Hardware :: Symmetric Multi-processing
Classifier: Topic :: System :: Logging
Classifier: Topic :: Software Development :: Debuggers
Classifier: Topic :: Software Development :: Libraries :: Python Modules
Requires-Python: >=3.6
License-File: LICENSE
